modules/__init__.py
modules/actions.py
modules/system/__init__.py
modules/system/controls.py
system_commander-0.7.dist-info/METADATA
system_commander-0.7.dist-info/WHEEL
system_commander-0.7.dist-info/entry_points.txt
system_commander-0.7.dist-info/top_level.txt
system_commander-0.7.dist-info/RECORD
