Metadata-Version: 2.1
Name: system-commander
Version: 0.7
Summary: Python package for controlling system actions
Home-page: https://git.selfmade.ninja/karthikeyanramesh/python-pip-packages/
Author: Karthikeyan
Author-email: karthikeyan02022003@gmail.com
